functions/__init__.py
functions/readConfig.py
functions/sqlite_data.py
theos_functions/__init__.py
theos_functions/date_time_functions.py
theos_functions/readConfig.py
theos_functions/sqlite_data.py
Theos_python_functions-0.0.6.2.dist-info/LICENSE
Theos_python_functions-0.0.6.2.dist-info/METADATA
Theos_python_functions-0.0.6.2.dist-info/WHEEL
Theos_python_functions-0.0.6.2.dist-info/top_level.txt
Theos_python_functions-0.0.6.2.dist-info/RECORD
