Metadata-Version: 2.1
Name: Theos-python-functions
Version: 0.0.6.2
Summary: Some nice to have python functions
Home-page: https://github.com/tvdsluijs/Theos-Python-Functions
Author: Theo van der Sluijs
Author-email: theo@vandersluijs.nl
License: UNKNOWN
Platform: UNKNOWN
Classifier: Programming Language :: Python :: 3
Classifier: License :: OSI Approved :: MIT License
Classifier: Operating System :: OS Independent
Requires-Python: >=3.6
